[
    {
      "country": "United States",
      "code": "US",
      "city": "Philadelphia",
      "latency": 15,
      "ip": "67.217.241.220",
      "flag": "🇺🇸"
    },
    {
    "country": "Belarus",
    "code": "BY",
    "city": "Minsk",
    "latency": 17,
    "ip": "193.47.42.199",
    "flag": "🇧🇾"
  },
    {
      "country": "Russia - under development",
      "code": "RU",
      "city": "Moscow",
      "latency": 33,
      "ip": "162.115.173.201",
      "flag": "🇷🇺",
      "availableProtocols": ["openVPN", "wireGuard", "ikev2"],
      "selectedProtocol": "ikev2"
    }
    }
  ]
